strpipe/__init__.py
strpipe/tests/__init__.py
strpipe/tests/test_dummy.py
strpipe-0.1.0.dist-info/METADATA
strpipe-0.1.0.dist-info/RECORD
strpipe-0.1.0.dist-info/WHEEL
strpipe-0.1.0.dist-info/top_level.txt
