Metadata-Version: 2.1
Name: strpipe
Version: 0.1.0
Summary: Reversible String Process Pipeline
Home-page: https://github.com/Yoctol/strpipe
Author: Yoctol Info
Author-email: cph@yoctol.com
License: MIT
Platform: UNKNOWN
Requires-Python: >=3.6
